pg_ormapping/__init__.py
pg_ormapping/define.py
pg_ormapping/field.py
pg_ormapping/obj.py
pg_ormapping-1.1.4.dist-info/METADATA
pg_ormapping-1.1.4.dist-info/WHEEL
pg_ormapping-1.1.4.dist-info/top_level.txt
pg_ormapping-1.1.4.dist-info/RECORD
